setup.py
lib/zoink_sftp.egg-info/PKG-INFO
lib/zoink_sftp.egg-info/SOURCES.txt
lib/zoink_sftp.egg-info/dependency_links.txt
lib/zoink_sftp.egg-info/requires.txt
lib/zoink_sftp.egg-info/top_level.txt
lib/zoinksftp/__init__.py
lib/zoinksftp/ssh.py
lib/zoinksftp/utils.py
lib/zoinksftp/doc/__init__.py
lib/zoinksftp/example/__init__.py
lib/zoinksftp/example/simple.py
lib/zoinksftp/tests/__init__.py
lib/zoinksftp/tests/testzoinksftp.py