Metadata-Version: 1.0
Name: zoink-sftp
Version: 0.1.0
Summary: Friendly Python SSH2 interface allowing easy file and directory transfer. This does not wrap the sftp command line tool
Home-page: UNKNOWN
Author: Zeth and Oisin Mulvihill
Author-email: oisin dot mulvihill at gmail com
License: LGPL
Platform: UNKNOWN
